{
    "-- Getting Started": {
        "type": "separator",
        "title": "Getting Started"
    },
    "index": {
        "title": "Introduction"
    },
    "install": "Installing Uffizzi",
    "quickstart": "Quickstart",
    "core-concepts": "Core Concepts",
    "cli": "CLI",
    "compose": {
        "title": "Compose",
        "display": "hidden"
    },
    "usage": "Using Uffizzi",
    "-- Use Cases": {
        "type": "separator",
        "title": "Use Cases / Guides"
    },
    "dev-environments": "Dev Environments",
    "testing": "Test Environments",
    "ci": "CI Recipes",
    "staging": "Staging Environments",
    "-- Resources": {
        "type": "separator",
        "title": "Resources"
    },
    "handbook": "Ephemeral Environments Handbook",
    "architecture": "Architecture",
    "ingress": "Uffizzi Ingress",
    "resource-quotas": "Resource Quotas",
    "compose-spec": "Uffizzi Compose",
    "troubleshooting": "Troubleshooting",
    "-- Products": {
        "type": "separator",
        "title": "Products"
    },
    "cloud": "Uffizzi Cloud",
    "enterprise": "Uffizzi Enterprise",
    "open-source": "Uffizzi Open Source",
    "products": {
        "title": "Products",
        "type": "menu",
        "items": {
            "cloud": {
                "title": "Uffizzi Cloud",
                "href": "/cloud"
            },
            "enterprise": {
                "title": "Uffizzi Enterprise",
                "href": "/enterprise"
            },
            "open-source": {
                "title": "Uffizzi Open Source",
                "href": "/open-source"
            }
        }
    },
    "showcase": {
        "title": "Showcase",
        "type": "menu",
        "items": {
            "backstage": {
                "title": "Backstage",
                "href": "/showcase/backstage"
            },
            "ingress-nginx": {
                "title": "Ingress Nginx",
                "href": "/testing/ingress-nginx"
            }
        }
    },
    "blog": {
        "type": "page",
        "title": "Blog",
        "href": "https://uffizzi.com/blog",
        "newWindow": true
    },
    "references": {
        "type": "page",
        "display": "hidden"
    },
    "virtual-cluster-environment": {
        "type": "page",
        "display": "hidden"
    }
}